MANIFEST.in
README.md
setup.py
dokus/__init__.py
pydokus.egg-info/PKG-INFO
pydokus.egg-info/SOURCES.txt
pydokus.egg-info/dependency_links.txt
pydokus.egg-info/top_level.txt