Metadata-Version: 1.0
Name: pydokus
Version: 0.8.0
Summary: pydokus is Python module for interacting with the Dokus REST API.
Home-page: https://github.com/funkbit/dokus-api
Author: Funkbit AS
Author-email: post@funkbit.no
License: BSD
Platform: UNKNOWN
Classifier: Development Status :: 4 - Beta
Classifier: Intended Audience :: Developers
Classifier: License :: OSI Approved :: BSD License
Classifier: Programming Language :: Python
Classifier: Programming Language :: Python :: 2.6
Classifier: Programming Language :: Python :: 2.7
Classifier: Topic :: Software Development :: Libraries :: Python Modules
